Workbook

Sheet Headcount
A1: Department | B1: Headcount
A2: Eng | B2: 40
A3: Sales | B3: 30
A4: G&A | B4: 20
A5: Support | B5: 10

Sheet Assumptions
A5: Subscription monthly growth | B5: 0.032
A12: Overhead | B12: 100000

Sheet Alloc
A1: Department | B1: Allocation
A2: Eng | B2: -999
A3: Sales | B3: -999
A4: G&A | B4: -999
A5: Support | B5: -999

Sheet Actuals
A1: Line Item | B1: Month | C1: Section | D1: Amount
A2: Subscription Revenue | B2: Jan-26 | C2: Revenue | D2: 225720
A3: Subscription Revenue | B3: Jan-26 | C3: Revenue | D3: 117040
A4: Subscription Revenue | B4: Jan-26 | C4: Revenue | D4: 75240
A5: Subscription Revenue | B5: Feb-26 | C5: Revenue | D5: 233874
A6: Subscription Revenue | B6: Feb-26 | C6: Revenue | D6: 121268
A7: Subscription Revenue | B7: Feb-26 | C7: Revenue | D7: 77958
A8: Subscription Revenue | B8: Mar-26 | C8: Revenue | D8: 248076
A9: Subscription Revenue | B9: Mar-26 | C9: Revenue | D9: 128632
A10: Subscription Revenue | B10: Mar-26 | C10: Revenue | D10: 82692
A11: Subscription Revenue | B11: Apr-26 | C11: Revenue | D11: 253638
A12: Subscription Revenue | B12: Apr-26 | C12: Revenue | D12: 131516
A13: Subscription Revenue | B13: Apr-26 | C13: Revenue | D13: 84546
... A163: Interest Expense | B163: Jun-26 | C163: Below the Line | D163: 5400

Sheet Forecast Inputs
A5: Line Item | B5: Method | C5: Monthly Growth | D5: Jul-26 | E5: Aug-26 | F5: Sep-26 | G5: Oct-26 | H5: Nov-26 | I5: Dec-26
A6: Subscription Revenue | B6: growth | C6: =Assumptions!B5
A7: Usage Revenue | B7: growth | C7: 0.0475
A8: Professional Services Rev | B8: manual | D8: 91000 | E8: 64000 | F8: 101000 | G8: 73000 | H8: 88000 | I8: 126000
A9: Hosting & Infrastructure | B9: growth | C9: 0.021
A10: Customer Support | B10: growth | C10: 0.0125
A11: Services Delivery | B11: manual | D11: 53500 | E11: 39000 | F11: 60500 | G11: 44000 | H11: 52000 | I11: 72000
A12: Sales & Marketing | B12: manual | D12: 181000 | E12: 176000 | F12: 204000 | G12: 188000 | H12: 232000 | I12: 195000
A13: Research & Development | B13: growth | C13: 0.014
A14: General & Administrative | B14: growth | C14: 0.0065
A15: People / Recruiting | B15: manual | D15: 24000 | E15: 0 | F15: 31000 | G15: 18000 | H15: 42000 | I15: 21000
A16: Depreciation & Amort. | B16: flat
A17: Interest Expense | B17: manual | D17: 5200 | E17: 5200 | F17: 5000 | G17: 5000 | H17: 4800 | I17: 4800

Sheet Line Definitions
A1: Line Item | B1: Section
A2: Subscription Revenue | B2: Revenue
A3: Usage Revenue | B3: Revenue
A4: Professional Services Rev | B4: Revenue
A5: Hosting & Infrastructure | B5: Cost of Revenue
A6: Customer Support | B6: Cost of Revenue
A7: Services Delivery | B7: Cost of Revenue
A8: Sales & Marketing | B8: Operating Expenses
A9: Research & Development | B9: Operating Expenses
A10: General & Administrative | B10: Operating Expenses
A11: People / Recruiting | B11: Operating Expenses
A12: Depreciation & Amort. | B12: Below the Line
A13: Interest Expense | B13: Below the Line

Sheet Forecast
A1: Line Item | B1: Section | C1: Method | D1: June Base | E1: Jul-26 | F1: Aug-26 | G1: Sep-26 | H1: Oct-26 | I1: Nov-26 | J1: Dec-26
A2: Subscription Revenue | B2: Revenue | C2: ='Forecast Inputs'!B6 | D2: =SUMIFS(Actuals!D2:D163,Actuals!A2:A163,A2,Actuals!B2:B163,"Jun-26") | E2: =IF(C2="manual",'Forecast Inputs'!D6,IF(C2="flat",D2,D2*(1+'Forecast Inputs'!C6)^1)) | F2: =IF(C2="manual",'Forecast Inputs'!E6,IF(C2="flat",D2,D2*(1+'Forecast Inputs'!C6)^2)) | G2: =IF(C2="manual",'Forecast Inputs'!F6,IF(C2="flat",D2,D2*(1+'Forecast Inputs'!C6)^3)) | H2: =IF(C2="manual",'Forecast Inputs'!G6,IF(C2="flat",D2,D2*(1+'Forecast Inputs'!C6)^4)) | I2: =IF(C2="manual",'Forecast Inputs'!H6,IF(C2="flat",D2,D2*(1+'Forecast Inputs'!C6)^5)) | J2: =IF(C2="manual",'Forecast Inputs'!I6,IF(C2="flat",D2,D2*(1+'Forecast Inputs'!C6)^6))
A3: Usage Revenue | B3: Revenue | C3: ='Forecast Inputs'!B7 | D3: =SUMIFS(Actuals!D2:D163,Actuals!A2:A163,A3,Actuals!B2:B163,"Jun-26") | E3: =IF(C3="manual",'Forecast Inputs'!D7,IF(C3="flat",D3,D3*(1+'Forecast Inputs'!C7)^1)) | F3: =IF(C3="manual",'Forecast Inputs'!E7,IF(C3="flat",D3,D3*(1+'Forecast Inputs'!C7)^2)) | G3: =IF(C3="manual",'Forecast Inputs'!F7,IF(C3="flat",D3,D3*(1+'Forecast Inputs'!C7)^3)) | H3: =IF(C3="manual",'Forecast Inputs'!G7,IF(C3="flat",D3,D3*(1+'Forecast Inputs'!C7)^4)) | I3: =IF(C3="manual",'Forecast Inputs'!H7,IF(C3="flat",D3,D3*(1+'Forecast Inputs'!C7)^5)) | J3: =IF(C3="manual",'Forecast Inputs'!I7,IF(C3="flat",D3,D3*(1+'Forecast Inputs'!C7)^6))
A4: Professional Services Rev | B4: Revenue | C4: ='Forecast Inputs'!B8 | D4: =SUMIFS(Actuals!D2:D163,Actuals!A2:A163,A4,Actuals!B2:B163,"Jun-26") | E4: =IF(C4="manual",'Forecast Inputs'!D8,IF(C4="flat",D4,D4*(1+'Forecast Inputs'!C8)^1)) | F4: =IF(C4="manual",'Forecast Inputs'!E8,IF(C4="flat",D4,D4*(1+'Forecast Inputs'!C8)^2)) | G4: =IF(C4="manual",'Forecast Inputs'!F8,IF(C4="flat",D4,D4*(1+'Forecast Inputs'!C8)^3)) | H4: =IF(C4="manual",'Forecast Inputs'!G8,IF(C4="flat",D4,D4*(1+'Forecast Inputs'!C8)^4)) | I4: =IF(C4="manual",'Forecast Inputs'!H8,IF(C4="flat",D4,D4*(1+'Forecast Inputs'!C8)^5)) | J4: =IF(C4="manual",'Forecast Inputs'!I8,IF(C4="flat",D4,D4*(1+'Forecast Inputs'!C8)^6))
A5: Hosting & Infrastructure | B5: Cost of Revenue | C5: ='Forecast Inputs'!B9 | D5: =SUMIFS(Actuals!D2:D163,Actuals!A2:A163,A5,Actuals!B2:B163,"Jun-26") | E5: =IF(C5="manual",'Forecast Inputs'!D9,IF(C5="flat",D5,D5*(1+'Forecast Inputs'!C9)^1)) | F5: =IF(C5="manual",'Forecast Inputs'!E9,IF(C5="flat",D5,D5*(1+'Forecast Inputs'!C9)^2)) | G5: =IF(C5="manual",'Forecast Inputs'!F9,IF(C5="flat",D5,D5*(1+'Forecast Inputs'!C9)^3)) | H5: =IF(C5="manual",'Forecast Inputs'!G9,IF(C5="flat",D5,D5*(1+'Forecast Inputs'!C9)^4)) | I5: =IF(C5="manual",'Forecast Inputs'!H9,IF(C5="flat",D5,D5*(1+'Forecast Inputs'!C9)^5)) | J5: =IF(C5="manual",'Forecast Inputs'!I9,IF(C5="flat",D5,D5*(1+'Forecast Inputs'!C9)^6))
A6: Customer Support | B6: Cost of Revenue | C6: ='Forecast Inputs'!B10 | D6: =SUMIFS(Actuals!D2:D163,Actuals!A2:A163,A6,Actuals!B2:B163,"Jun-26") | E6: =IF(C6="manual",'Forecast Inputs'!D10,IF(C6="flat",D6,D6*(1+'Forecast Inputs'!C10)^1)) | F6: =IF(C6="manual",'Forecast Inputs'!E10,IF(C6="flat",D6,D6*(1+'Forecast Inputs'!C10)^2)) | G6: =IF(C6="manual",'Forecast Inputs'!F10,IF(C6="flat",D6,D6*(1+'Forecast Inputs'!C10)^3)) | H6: =IF(C6="manual",'Forecast Inputs'!G10,IF(C6="flat",D6,D6*(1+'Forecast Inputs'!C10)^4)) | I6: =IF(C6="manual",'Forecast Inputs'!H10,IF(C6="flat",D6,D6*(1+'Forecast Inputs'!C10)^5)) | J6: =IF(C6="manual",'Forecast Inputs'!I10,IF(C6="flat",D6,D6*(1+'Forecast Inputs'!C10)^6))
A7: Services Delivery | B7: Cost of Revenue | C7: ='Forecast Inputs'!B11 | D7: =SUMIFS(Actuals!D2:D163,Actuals!A2:A163,A7,Actuals!B2:B163,"Jun-26") | E7: =IF(C7="manual",'Forecast Inputs'!D11,IF(C7="flat",D7,D7*(1+'Forecast Inputs'!C11)^1)) | F7: =IF(C7="manual",'Forecast Inputs'!E11,IF(C7="flat",D7,D7*(1+'Forecast Inputs'!C11)^2)) | G7: =IF(C7="manual",'Forecast Inputs'!F11,IF(C7="flat",D7,D7*(1+'Forecast Inputs'!C11)^3)) | H7: =IF(C7="manual",'Forecast Inputs'!G11,IF(C7="flat",D7,D7*(1+'Forecast Inputs'!C11)^4)) | I7: =IF(C7="manual",'Forecast Inputs'!H11,IF(C7="flat",D7,D7*(1+'Forecast Inputs'!C11)^5)) | J7: =IF(C7="manual",'Forecast Inputs'!I11,IF(C7="flat",D7,D7*(1+'Forecast Inputs'!C11)^6))
A8: Sales & Marketing | B8: Operating Expenses | C8: ='Forecast Inputs'!B12 | D8: =SUMIFS(Actuals!D2:D163,Actuals!A2:A163,A8,Actuals!B2:B163,"Jun-26") | E8: =IF(C8="manual",'Forecast Inputs'!D12,IF(C8="flat",D8,D8*(1+'Forecast Inputs'!C12)^1)) | F8: =IF(C8="manual",'Forecast Inputs'!E12,IF(C8="flat",D8,D8*(1+'Forecast Inputs'!C12)^2)) | G8: =IF(C8="manual",'Forecast Inputs'!F12,IF(C8="flat",D8,D8*(1+'Forecast Inputs'!C12)^3)) | H8: =IF(C8="manual",'Forecast Inputs'!G12,IF(C8="flat",D8,D8*(1+'Forecast Inputs'!C12)^4)) | I8: =IF(C8="manual",'Forecast Inputs'!H12,IF(C8="flat",D8,D8*(1+'Forecast Inputs'!C12)^5)) | J8: =IF(C8="manual",'Forecast Inputs'!I12,IF(C8="flat",D8,D8*(1+'Forecast Inputs'!C12)^6))
A9: Research & Development | B9: Operating Expenses | C9: ='Forecast Inputs'!B13 | D9: =SUMIFS(Actuals!D2:D163,Actuals!A2:A163,A9,Actuals!B2:B163,"Jun-26") | E9: =IF(C9="manual",'Forecast Inputs'!D13,IF(C9="flat",D9,D9*(1+'Forecast Inputs'!C13)^1)) | F9: =IF(C9="manual",'Forecast Inputs'!E13,IF(C9="flat",D9,D9*(1+'Forecast Inputs'!C13)^2)) | G9: =IF(C9="manual",'Forecast Inputs'!F13,IF(C9="flat",D9,D9*(1+'Forecast Inputs'!C13)^3)) | H9: =IF(C9="manual",'Forecast Inputs'!G13,IF(C9="flat",D9,D9*(1+'Forecast Inputs'!C13)^4)) | I9: =IF(C9="manual",'Forecast Inputs'!H13,IF(C9="flat",D9,D9*(1+'Forecast Inputs'!C13)^5)) | J9: =IF(C9="manual",'Forecast Inputs'!I13,IF(C9="flat",D9,D9*(1+'Forecast Inputs'!C13)^6))
A10: General & Administrative | B10: Operating Expenses | C10: ='Forecast Inputs'!B14 | D10: =SUMIFS(Actuals!D2:D163,Actuals!A2:A163,A10,Actuals!B2:B163,"Jun-26") | E10: =IF(C10="manual",'Forecast Inputs'!D14,IF(C10="flat",D10,D10*(1+'Forecast Inputs'!C14)^1)) | F10: =IF(C10="manual",'Forecast Inputs'!E14,IF(C10="flat",D10,D10*(1+'Forecast Inputs'!C14)^2)) | G10: =IF(C10="manual",'Forecast Inputs'!F14,IF(C10="flat",D10,D10*(1+'Forecast Inputs'!C14)^3)) | H10: =IF(C10="manual",'Forecast Inputs'!G14,IF(C10="flat",D10,D10*(1+'Forecast Inputs'!C14)^4)) | I10: =IF(C10="manual",'Forecast Inputs'!H14,IF(C10="flat",D10,D10*(1+'Forecast Inputs'!C14)^5)) | J10: =IF(C10="manual",'Forecast Inputs'!I14,IF(C10="flat",D10,D10*(1+'Forecast Inputs'!C14)^6))
A11: People / Recruiting | B11: Operating Expenses | C11: ='Forecast Inputs'!B15 | D11: =SUMIFS(Actuals!D2:D163,Actuals!A2:A163,A11,Actuals!B2:B163,"Jun-26") | E11: =IF(C11="manual",'Forecast Inputs'!D15,IF(C11="flat",D11,D11*(1+'Forecast Inputs'!C15)^1)) | F11: =IF(C11="manual",'Forecast Inputs'!E15,IF(C11="flat",D11,D11*(1+'Forecast Inputs'!C15)^2)) | G11: =IF(C11="manual",'Forecast Inputs'!F15,IF(C11="flat",D11,D11*(1+'Forecast Inputs'!C15)^3)) | H11: =IF(C11="manual",'Forecast Inputs'!G15,IF(C11="flat",D11,D11*(1+'Forecast Inputs'!C15)^4)) | I11: =IF(C11="manual",'Forecast Inputs'!H15,IF(C11="flat",D11,D11*(1+'Forecast Inputs'!C15)^5)) | J11: =IF(C11="manual",'Forecast Inputs'!I15,IF(C11="flat",D11,D11*(1+'Forecast Inputs'!C15)^6))
A12: Depreciation & Amort. | B12: Below the Line | C12: ='Forecast Inputs'!B16 | D12: =SUMIFS(Actuals!D2:D163,Actuals!A2:A163,A12,Actuals!B2:B163,"Jun-26") | E12: =IF(C12="manual",'Forecast Inputs'!D16,IF(C12="flat",D12,D12*(1+'Forecast Inputs'!C16)^1)) | F12: =IF(C12="manual",'Forecast Inputs'!E16,IF(C12="flat",D12,D12*(1+'Forecast Inputs'!C16)^2)) | G12: =IF(C12="manual",'Forecast Inputs'!F16,IF(C12="flat",D12,D12*(1+'Forecast Inputs'!C16)^3)) | H12: =IF(C12="manual",'Forecast Inputs'!G16,IF(C12="flat",D12,D12*(1+'Forecast Inputs'!C16)^4)) | I12: =IF(C12="manual",'Forecast Inputs'!H16,IF(C12="flat",D12,D12*(1+'Forecast Inputs'!C16)^5)) | J12: =IF(C12="manual",'Forecast Inputs'!I16,IF(C12="flat",D12,D12*(1+'Forecast Inputs'!C16)^6))
A13: Interest Expense | B13: Below the Line | C13: ='Forecast Inputs'!B17 | D13: =SUMIFS(Actuals!D2:D163,Actuals!A2:A163,A13,Actuals!B2:B163,"Jun-26") | E13: =IF(C13="manual",'Forecast Inputs'!D17,IF(C13="flat",D13,D13*(1+'Forecast Inputs'!C17)^1)) | F13: =IF(C13="manual",'Forecast Inputs'!E17,IF(C13="flat",D13,D13*(1+'Forecast Inputs'!C17)^2)) | G13: =IF(C13="manual",'Forecast Inputs'!F17,IF(C13="flat",D13,D13*(1+'Forecast Inputs'!C17)^3)) | H13: =IF(C13="manual",'Forecast Inputs'!G17,IF(C13="flat",D13,D13*(1+'Forecast Inputs'!C17)^4)) | I13: =IF(C13="manual",'Forecast Inputs'!H17,IF(C13="flat",D13,D13*(1+'Forecast Inputs'!C17)^5)) | J13: =IF(C13="manual",'Forecast Inputs'!I17,IF(C13="flat",D13,D13*(1+'Forecast Inputs'!C17)^6))

Sheet P&L
M33: Annual Net Income | N33: =(SUMIFS(Actuals!D2:D163,Actuals!C2:C163,"Revenue")+SUMIFS(Forecast!E2:E13,Forecast!B2:B13,"Revenue")+SUMIFS(Forecast!F2:F13,Forecast!B2:B13,"Revenue")+SUMIFS(Forecast!G2:G13,Forecast!B2:B13,"Revenue")+SUMIFS(Forecast!H2:H13,Forecast!B2:B13,"Revenue")+SUMIFS(Forecast!I2:I13,Forecast!B2:B13,"Revenue")+SUMIFS(Forecast!J2:J13,Forecast!B2:B13,"Revenue"))-(SUMIFS(Actuals!D2:D163,Actuals!C2:C163,"Cost of Revenue")+SUMIFS(Forecast!E2:E13,Forecast!B2:B13,"Cost of Revenue")+SUMIFS(Forecast!F2:F13,Forecast!B2:B13,"Cost of Revenue")+SUMIFS(Forecast!G2:G13,Forecast!B2:B13,"Cost of Revenue")+SUMIFS(Forecast!H2:H13,Forecast!B2:B13,"Cost of Revenue")+SUMIFS(Forecast!I2:I13,Forecast!B2:B13,"Cost of Revenue")+SUMIFS(Forecast!J2:J13,Forecast!B2:B13,"Cost of Revenue"))-(SUMIFS(Actuals!D2:D163,Actuals!C2:C163,"Operating Expenses")+SUMIFS(Forecast!E2:E13,Forecast!B2:B13,"Operating Expenses")+SUMIFS(Forecast!F2:F13,Forecast!B2:B13,"Operating Expenses")+SUMIFS(Forecast!G2:G13,Forecast!B2:B13,"Operating Expenses")+SUMIFS(Forecast!H2:H13,Forecast!B2:B13,"Operating Expenses")+SUMIFS(Forecast!I2:I13,Forecast!B2:B13,"Operating Expenses")+SUMIFS(Forecast!J2:J13,Forecast!B2:B13,"Operating Expenses"))-(SUMIFS(Actuals!D2:D163,Actuals!C2:C163,"Below the Line")+SUMIFS(Forecast!E2:E13,Forecast!B2:B13,"Below the Line")+SUMIFS(Forecast!F2:F13,Forecast!B2:B13,"Below the Line")+SUMIFS(Forecast!G2:G13,Forecast!B2:B13,"Below the Line")+SUMIFS(Forecast!H2:H13,Forecast!B2:B13,"Below the Line")+SUMIFS(Forecast!I2:I13,Forecast!B2:B13,"Below the Line")+SUMIFS(Forecast!J2:J13,Forecast!B2:B13,"Below the Line"))
