Workbook

Sheet P&L
A1: FY26 Monthly P&L — Actuals Jan-Jun, Forecast Jul-Dec
B3: ACTUALS | H3: FORECAST
A4: Line Item | B4: Jan-26 | C4: Feb-26 | D4: Mar-26 | E4: Apr-26 | F4: May-26 | G4: Jun-26 | H4: Jul-26 | I4: Aug-26 | J4: Sep-26 | K4: Oct-26 | L4: Nov-26 | M4: Dec-26 | N4: FY26
A6: Revenue
A7: Subscription Revenue | B7: =SUMIFS(Data!$F:$F,Data!$C:$C,$A7,Data!$B:$B,B$4) -> 477963 | C7: =SUMIFS(Data!$F:$F,Data!$C:$C,$A7,Data!$B:$B,C$4) -> 484010 | D7: =SUMIFS(Data!$F:$F,Data!$C:$C,$A7,Data!$B:$B,D$4) -> 489715 | E7: =SUMIFS(Data!$F:$F,Data!$C:$C,$A7,Data!$B:$B,E$4) -> 497737 | F7: =SUMIFS(Data!$F:$F,Data!$C:$C,$A7,Data!$B:$B,F$4) -> 501925 | G7: =SUMIFS(Data!$F:$F,Data!$C:$C,$A7,Data!$B:$B,G$4) -> 508824 | H7: =G7*(1+Assumptions!$B$5) -> 524088.72 | I7: =H7*(1+Assumptions!$B$5) -> 539811.38 | J7: =I7*(1+Assumptions!$B$5) -> 556005.72 | K7: =J7*(1+Assumptions!$B$5) -> 572685.89 | L7: =K7*(1+Assumptions!$B$5) -> 589866.47 | M7: =L7*(1+Assumptions!$B$5) -> 607562.47 | N7: =SUM(B7:M7) -> 6350194.7
A8: Professional Services | B8: =SUMIFS(Data!$F:$F,Data!$C:$C,$A8,Data!$B:$B,B$4) -> 61560 | C8: =SUMIFS(Data!$F:$F,Data!$C:$C,$A8,Data!$B:$B,C$4) -> 65207 | D8: =SUMIFS(Data!$F:$F,Data!$C:$C,$A8,Data!$B:$B,D$4) -> 62726 | E8: =SUMIFS(Data!$F:$F,Data!$C:$C,$A8,Data!$B:$B,E$4) -> 66702 | F8: =SUMIFS(Data!$F:$F,Data!$C:$C,$A8,Data!$B:$B,F$4) -> 62768 | G8: =SUMIFS(Data!$F:$F,Data!$C:$C,$A8,Data!$B:$B,G$4) -> 67981 | H8: 70000 | I8: 64000 | J8: 78000 | K8: 66000 | L8: 74000 | M8: 95000 | N8: =SUM(B8:M8) -> 833944
A9: Total Revenue | B9: =SUM(B7:B8) -> 539523 | C9: =SUM(C7:C8) -> 549217 | D9: =SUM(D7:D8) -> 552441 | E9: =SUM(E7:E8) -> 564439 | F9: =SUM(F7:F8) -> 564693 | G9: =SUM(G7:G8) -> 576805 | H9: =SUM(H7:H8) -> 594088.72 | I9: =SUM(I7:I8) -> 603811.38 | ... N9: =SUM(N7:N8) -> 7184138.7
A11: Cost of Revenue
A12: Hosting & Infrastructure | B12: =SUMIFS(Data!$F:$F,Data!$C:$C,$A12,Data!$B:$B,B$4) -> 59797 | C12: =SUMIFS(Data!$F:$F,Data!$C:$C,$A12,Data!$B:$B,C$4) -> 62760 | D12: =SUMIFS(Data!$F:$F,Data!$C:$C,$A12,Data!$B:$B,D$4) -> 63187 | E12: =SUMIFS(Data!$F:$F,Data!$C:$C,$A12,Data!$B:$B,E$4) -> 64866 | F12: =SUMIFS(Data!$F:$F,Data!$C:$C,$A12,Data!$B:$B,F$4) -> 64475 | G12: =SUMIFS(Data!$F:$F,Data!$C:$C,$A12,Data!$B:$B,G$4) -> 66617 | H12: =G12*(1+Assumptions!$B$6) -> 67616.255 | I12: =H12*(1+Assumptions!$B$6) -> 68630.499 | J12: =I12*(1+Assumptions!$B$6) -> 69659.956 | K12: =J12*(1+Assumptions!$B$6) -> 70704.856 | L12: =K12*(1+Assumptions!$B$6) -> 71765.428 | M12: =L12*(1+Assumptions!$B$6) -> 72841.91 | N12: =SUM(B12:M12) -> 802920.9
A13: Customer Support | B13: =SUMIFS(Data!$F:$F,Data!$C:$C,$A13,Data!$B:$B,B$4) -> 44144 | C13: =SUMIFS(Data!$F:$F,Data!$C:$C,$A13,Data!$B:$B,C$4) -> 45128 | D13: =SUMIFS(Data!$F:$F,Data!$C:$C,$A13,Data!$B:$B,D$4) -> 43729 | E13: =SUMIFS(Data!$F:$F,Data!$C:$C,$A13,Data!$B:$B,E$4) -> 42342 | F13: =SUMIFS(Data!$F:$F,Data!$C:$C,$A13,Data!$B:$B,F$4) -> 42788 | G13: =SUMIFS(Data!$F:$F,Data!$C:$C,$A13,Data!$B:$B,G$4) -> 46062 | H13: =G13*(1+Assumptions!$B$7) -> 46522.62 | I13: =H13*(1+Assumptions!$B$7) -> 46987.846 | J13: =I13*(1+Assumptions!$B$7) -> 47457.725 | K13: =J13*(1+Assumptions!$B$7) -> 47932.302 | L13: =K13*(1+Assumptions!$B$7) -> 48411.625 | M13: =L13*(1+Assumptions!$B$7) -> 48895.741 | N13: =SUM(B13:M13) -> 550400.86
A14: Total Cost of Revenue | B14: =SUM(B12:B13) -> 103941 | C14: =SUM(C12:C13) -> 107888 | D14: =SUM(D12:D13) -> 106916 | E14: =SUM(E12:E13) -> 107208 | F14: =SUM(F12:F13) -> 107263 | G14: =SUM(G12:G13) -> 112679 | H14: =SUM(H12:H13) -> 114138.88 | I14: =SUM(I12:I13) -> 115618.35 | ... N14: =SUM(N12:N13) -> 1353321.8
A15: Gross Profit | B15: =B9-B14 -> 435582 | C15: =C9-C14 -> 441329 | D15: =D9-D14 -> 445525 | E15: =E9-E14 -> 457231 | F15: =F9-F14 -> 457430 | G15: =G9-G14 -> 464126 | H15: =H9-H14 -> 479949.84 | I15: =I9-I14 -> 488193.04 | ... N15: =N9-N14 -> 5830816.9
A16: Gross Margin % | B16: =IF(B9=0,0,B15/B9) -> 0.80734649 | C16: =IF(C9=0,0,C15/C9) -> 0.80356034 | D16: =IF(D9=0,0,D15/D9) -> 0.80646621 | E16: =IF(E9=0,0,E15/E9) -> 0.81006273 | F16: =IF(F9=0,0,F15/F9) -> 0.81005077 | G16: =IF(G9=0,0,G15/G9) -> 0.80464975 | H16: =IF(H9=0,0,H15/H9) -> 0.80787571 | I16: =IF(I9=0,0,I15/I9) -> 0.8085191 | ... N16: =IF(N9=0,0,N15/N9) -> 0.81162366
A18: Operating Expenses
A19: Sales & Marketing | B19: =SUMIFS(Data!$F:$F,Data!$C:$C,$A19,Data!$B:$B,B$4) -> 159308 | C19: =SUMIFS(Data!$F:$F,Data!$C:$C,$A19,Data!$B:$B,C$4) -> 160004 | D19: =SUMIFS(Data!$F:$F,Data!$C:$C,$A19,Data!$B:$B,D$4) -> 162405 | E19: =SUMIFS(Data!$F:$F,Data!$C:$C,$A19,Data!$B:$B,E$4) -> 164658 | F19: =SUMIFS(Data!$F:$F,Data!$C:$C,$A19,Data!$B:$B,F$4) -> 167390 | G19: =SUMIFS(Data!$F:$F,Data!$C:$C,$A19,Data!$B:$B,G$4) -> 166327 | H19: =G19*(1+Assumptions!$B$8) -> 169653.54 | I19: =H19*(1+Assumptions!$B$8) -> 173046.61 | J19: =I19*(1+Assumptions!$B$8) -> 176507.54 | K19: =J19*(1+Assumptions!$B$8) -> 180037.69 | L19: =K19*(1+Assumptions!$B$8) -> 183638.45 | M19: =L19*(1+Assumptions!$B$8) -> 187311.22 | N19: =SUM(B19:M19) -> 2050287.1
A20: Research & Development | B20: =SUMIFS(Data!$F:$F,Data!$C:$C,$A20,Data!$B:$B,B$4) -> 173091 | C20: =SUMIFS(Data!$F:$F,Data!$C:$C,$A20,Data!$B:$B,C$4) -> 172005 | D20: =SUMIFS(Data!$F:$F,Data!$C:$C,$A20,Data!$B:$B,D$4) -> 174538 | E20: =SUMIFS(Data!$F:$F,Data!$C:$C,$A20,Data!$B:$B,E$4) -> 176545 | F20: =SUMIFS(Data!$F:$F,Data!$C:$C,$A20,Data!$B:$B,F$4) -> 176903 | G20: =SUMIFS(Data!$F:$F,Data!$C:$C,$A20,Data!$B:$B,G$4) -> 180207 | H20: =G20*(1+Assumptions!$B$9) -> 182009.07 | I20: =H20*(1+Assumptions!$B$9) -> 183829.16 | J20: =I20*(1+Assumptions!$B$9) -> 185667.45 | K20: =J20*(1+Assumptions!$B$9) -> 187524.13 | L20: =K20*(1+Assumptions!$B$9) -> 189399.37 | M20: =L20*(1+Assumptions!$B$9) -> 191293.36 | N20: =SUM(B20:M20) -> 2173011.5
A21: General & Administrative | B21: =SUMIFS(Data!$F:$F,Data!$C:$C,$A21,Data!$B:$B,B$4) -> 69163 | C21: =SUMIFS(Data!$F:$F,Data!$C:$C,$A21,Data!$B:$B,C$4) -> 68750 | D21: =SUMIFS(Data!$F:$F,Data!$C:$C,$A21,Data!$B:$B,D$4) -> 69275 | E21: =SUMIFS(Data!$F:$F,Data!$C:$C,$A21,Data!$B:$B,E$4) -> 73163 | F21: =SUMIFS(Data!$F:$F,Data!$C:$C,$A21,Data!$B:$B,F$4) -> 73991 | G21: =SUMIFS(Data!$F:$F,Data!$C:$C,$A21,Data!$B:$B,G$4) -> 73586 | H21: =G21*(1+Assumptions!$B$10) -> 73953.93 | I21: =H21*(1+Assumptions!$B$10) -> 74323.7 | J21: =I21*(1+Assumptions!$B$10) -> 74695.318 | K21: =J21*(1+Assumptions!$B$10) -> 75068.795 | L21: =K21*(1+Assumptions!$B$10) -> 75444.139 | M21: =L21*(1+Assumptions!$B$10) -> 75821.359 | N21: =SUM(B21:M21) -> 877235.24
A22: Rent & Facilities | B22: =SUMIFS(Data!$F:$F,Data!$C:$C,$A22,Data!$B:$B,B$4) -> 32000 | C22: =SUMIFS(Data!$F:$F,Data!$C:$C,$A22,Data!$B:$B,C$4) -> 32000 | D22: =SUMIFS(Data!$F:$F,Data!$C:$C,$A22,Data!$B:$B,D$4) -> 32000 | E22: =SUMIFS(Data!$F:$F,Data!$C:$C,$A22,Data!$B:$B,E$4) -> 32000 | F22: =SUMIFS(Data!$F:$F,Data!$C:$C,$A22,Data!$B:$B,F$4) -> 32000 | G22: =SUMIFS(Data!$F:$F,Data!$C:$C,$A22,Data!$B:$B,G$4) -> 32000 | H22: =G22 -> 32000 | I22: =H22 -> 32000 | J22: =I22 -> 32000 | K22: =J22 -> 32000 | L22: =K22 -> 32000 | M22: =L22 -> 32000 | N22: =SUM(B22:M22) -> 384000
A23: Total Operating Expenses | B23: =SUM(B19:B22) -> 433562 | C23: =SUM(C19:C22) -> 432759 | D23: =SUM(D19:D22) -> 438218 | E23: =SUM(E19:E22) -> 446366 | F23: =SUM(F19:F22) -> 450284 | G23: =SUM(G19:G22) -> 452120 | H23: =SUM(H19:H22) -> 457616.54 | I23: =SUM(I19:I22) -> 463199.47 | ... N23: =SUM(N19:N22) -> 5484533.8
A24: EBITDA | B24: =B15-B23 -> 2020 | C24: =C15-C23 -> 8570 | D24: =D15-D23 -> 7307 | E24: =E15-E23 -> 10865 | F24: =F15-F23 -> 7146 | G24: =G15-G23 -> 12006 | H24: =H15-H23 -> 22333.305 | I24: =I15-I23 -> 24993.565 | ... N24: =N15-N23 -> 346283.06
A26: Below the Line
A27: Interest Expense | B27: =SUMIFS(Data!$F:$F,Data!$C:$C,$A27,Data!$B:$B,B$4) -> 6500 | C27: =SUMIFS(Data!$F:$F,Data!$C:$C,$A27,Data!$B:$B,C$4) -> 6500 | D27: =SUMIFS(Data!$F:$F,Data!$C:$C,$A27,Data!$B:$B,D$4) -> 6500 | E27: =SUMIFS(Data!$F:$F,Data!$C:$C,$A27,Data!$B:$B,E$4) -> 6500 | F27: =SUMIFS(Data!$F:$F,Data!$C:$C,$A27,Data!$B:$B,F$4) -> 6500 | G27: =SUMIFS(Data!$F:$F,Data!$C:$C,$A27,Data!$B:$B,G$4) -> 6500 | H27: =G27 -> 6500 | I27: =H27 -> 6500 | J27: =I27 -> 6500 | K27: =J27 -> 6500 | L27: =K27 -> 6500 | M27: =L27 -> 6500 | N27: =SUM(B27:M27) -> 78000
A28: Income Tax | B28: =SUMIFS(Data!$F:$F,Data!$C:$C,$A28,Data!$B:$B,B$4) -> 10708 | C28: =SUMIFS(Data!$F:$F,Data!$C:$C,$A28,Data!$B:$B,C$4) -> 11194 | D28: =SUMIFS(Data!$F:$F,Data!$C:$C,$A28,Data!$B:$B,D$4) -> 8205 | E28: =SUMIFS(Data!$F:$F,Data!$C:$C,$A28,Data!$B:$B,E$4) -> 10474 | F28: =SUMIFS(Data!$F:$F,Data!$C:$C,$A28,Data!$B:$B,F$4) -> 10328 | G28: =SUMIFS(Data!$F:$F,Data!$C:$C,$A28,Data!$B:$B,G$4) -> 11343 | H28: 11000 | I28: 11500 | J28: 12000 | K28: 12500 | L28: 13000 | M28: 21000 | N28: =SUM(B28:M28) -> 143252
A29: Total Below the Line | B29: =SUM(B27:B28) -> 17208 | C29: =SUM(C27:C28) -> 17694 | D29: =SUM(D27:D28) -> 14705 | E29: =SUM(E27:E28) -> 16974 | F29: =SUM(F27:F28) -> 16828 | G29: =SUM(G27:G28) -> 17843 | H29: =SUM(H27:H28) -> 17500 | I29: =SUM(I27:I28) -> 18000 | ... N29: =SUM(N27:N28) -> 221252
A31: Net Income | B31: =B24-B29 -> -15188 | C31: =C24-C29 -> -9124 | D31: =D24-D29 -> -7398 | E31: =E24-E29 -> -6109 | F31: =F24-F29 -> -9682 | G31: =G24-G29 -> -5837 | H31: =H24-H29 -> 4833.305 | I31: =I24-I29 -> 6993.5654 | ... N31: =N24-N29 -> 125031.06

Sheet Data
A1: Date | B1: Month | C1: Line Item | D1: Department | E1: Vendor | F1: Amount
A2: 46025 | B2: Jan-26 | C2: Subscription Revenue | D2: Revenue | E2: Enterprise | F2: 159321
A3: 46034 | B3: Jan-26 | C3: Subscription Revenue | D3: Revenue | E3: Mid-Market | F3: 159321
A4: 46043 | B4: Jan-26 | C4: Subscription Revenue | D4: Revenue | E4: SMB | F4: 159321
A5: 46056 | B5: Feb-26 | C5: Subscription Revenue | D5: Revenue | E5: Enterprise | F5: 161336.67
A6: 46065 | B6: Feb-26 | C6: Subscription Revenue | D6: Revenue | E6: Mid-Market | F6: 161336.67
A7: 46074 | B7: Feb-26 | C7: Subscription Revenue | D7: Revenue | E7: SMB | F7: 161336.66
A8: 46084 | B8: Mar-26 | C8: Subscription Revenue | D8: Revenue | E8: Enterprise | F8: 163238.33
A9: 46093 | B9: Mar-26 | C9: Subscription Revenue | D9: Revenue | E9: Mid-Market | F9: 163238.33
A10: 46102 | B10: Mar-26 | C10: Subscription Revenue | D10: Revenue | E10: SMB | F10: 163238.34
A11: 46115 | B11: Apr-26 | C11: Subscription Revenue | D11: Revenue | E11: Enterprise | F11: 165912.33
A12: 46124 | B12: Apr-26 | C12: Subscription Revenue | D12: Revenue | E12: Mid-Market | F12: 165912.33
A13: 46133 | B13: Apr-26 | C13: Subscription Revenue | D13: Revenue | E13: SMB | F13: 165912.34
... A157: 46185 | B157: Jun-26 | C157: Income Tax | D157: Finance | E157: IRS | F157: 5671.5

Sheet Assumptions
A1: Forecast Drivers (monthly growth, applied Jul-Dec)
A4: Driver | B4: Monthly Rate | C4: Basis
A5: Subscription Revenue growth | B5: 0.03 | C5: prior month x (1+rate)
A6: Hosting & Infrastructure growth | B6: 0.015 | C6: prior month x (1+rate)
A7: Customer Support growth | B7: 0.01 | C7: prior month x (1+rate)
A8: Sales & Marketing growth | B8: 0.02 | C8: prior month x (1+rate)
A9: R&D growth | B9: 0.01 | C9: prior month x (1+rate)
A10: G&A growth | B10: 0.005 | C10: prior month x (1+rate)
