Workbook

Sheet Budget
A1: Retail Budget — FY26 (Q1-Q2 actual, Q3-Q4 budget)
A4: Account | B4: Q3 FY25 | C4: Q4 FY25 | D4: Q1 FY26 | E4: Q2 FY26 | F4: Q3 FY26 Bud | G4: Q4 FY26 Bud | H4: FY26 Total | I4: FY26 vs FY25 H2 %
A6: Net Sales
A7: In-Store Sales | B7: =SUMIFS('GL Detail'!$E:$E,'GL Detail'!$C:$C,$A7,'GL Detail'!$A:$A,B$4) -> 2258850.7 | C7: =SUMIFS('GL Detail'!$E:$E,'GL Detail'!$C:$C,$A7,'GL Detail'!$A:$A,C$4) -> 3237986.4 | D7: =SUMIFS('GL Detail'!$E:$E,'GL Detail'!$C:$C,$A7,'GL Detail'!$A:$A,D$4) -> 2149541.9 | E7: =SUMIFS('GL Detail'!$E:$E,'GL Detail'!$C:$C,$A7,'GL Detail'!$A:$A,E$4) -> 2460059.9 | F7: =B7*(1+Drivers!$B$4) -> 2349204.7 | G7: =C7*(1+Drivers!$B$4) -> 3367505.9 | H7: =SUM(D7:G7) -> 10326312 | I7: =IFERROR((F7+G7)/(B7+C7)-1,"n/a") -> 0.04
A8: E-Commerce Sales | B8: =SUMIFS('GL Detail'!$E:$E,'GL Detail'!$C:$C,$A8,'GL Detail'!$A:$A,B$4) -> 862108.13 | C8: =SUMIFS('GL Detail'!$E:$E,'GL Detail'!$C:$C,$A8,'GL Detail'!$A:$A,C$4) -> 1240100 | D8: =SUMIFS('GL Detail'!$E:$E,'GL Detail'!$C:$C,$A8,'GL Detail'!$A:$A,D$4) -> 805863.29 | E8: =SUMIFS('GL Detail'!$E:$E,'GL Detail'!$C:$C,$A8,'GL Detail'!$A:$A,E$4) -> 915394.83 | F8: =B8*(1+Drivers!$B$5) -> 965561.11 | G8: =C8*(1+Drivers!$B$5) -> 1388912 | H8: =SUM(D8:G8) -> 4075731.2 | I8: =IFERROR((F8+G8)/(B8+C8)-1,"n/a") -> 0.12
A9: Total Net Sales | B9: =SUM(B7:B8) -> 3120958.8 | C9: =SUM(C7:C8) -> 4478086.4 | D9: =SUM(D7:D8) -> 2955405.2 | E9: =SUM(E7:E8) -> 3375454.8 | F9: =SUM(F7:F8) -> 3314765.8 | G9: =SUM(G7:G8) -> 4756417.9 | H9: =SUM(D9:G9) -> 14402044 | I9: =IFERROR((F9+G9)/(B9+C9)-1,"n/a") -> 0.062131287
A11: COGS
A12: Merchandise Cost | B12: =SUMIFS('GL Detail'!$E:$E,'GL Detail'!$C:$C,$A12,'GL Detail'!$A:$A,B$4) -> 1915539.4 | C12: =SUMIFS('GL Detail'!$E:$E,'GL Detail'!$C:$C,$A12,'GL Detail'!$A:$A,C$4) -> 2752143.2 | D12: =SUMIFS('GL Detail'!$E:$E,'GL Detail'!$C:$C,$A12,'GL Detail'!$A:$A,D$4) -> 1815876.1 | E12: =SUMIFS('GL Detail'!$E:$E,'GL Detail'!$C:$C,$A12,'GL Detail'!$A:$A,E$4) -> 2074631.5 | F12: =F9*Drivers!$B$6 -> 2038581 | G12: =G9*Drivers!$B$6 -> 2925197 | H12: =SUM(D12:G12) -> 8854285.6 | I12: =IFERROR((F12+G12)/(B12+C12)-1,"n/a") -> 0.063435191
A13: Shrink | B13: =SUMIFS('GL Detail'!$E:$E,'GL Detail'!$C:$C,$A13,'GL Detail'!$A:$A,B$4) -> 43683.75 | C13: =SUMIFS('GL Detail'!$E:$E,'GL Detail'!$C:$C,$A13,'GL Detail'!$A:$A,C$4) -> 62936.8 | D13: =SUMIFS('GL Detail'!$E:$E,'GL Detail'!$C:$C,$A13,'GL Detail'!$A:$A,D$4) -> 41472.07 | E13: =SUMIFS('GL Detail'!$E:$E,'GL Detail'!$C:$C,$A13,'GL Detail'!$A:$A,E$4) -> 47241.65 | F13: =F9*Drivers!$B$7 -> 46406.721 | G13: =G9*Drivers!$B$7 -> 66589.85 | H13: =SUM(D13:G13) -> 201710.29 | I13: =IFERROR((F13+G13)/(B13+C13)-1,"n/a") -> 0.059801053
A14: Total COGS | B14: =SUM(B12:B13) -> 1959223.1 | C14: =SUM(C12:C13) -> 2815080 | D14: =SUM(D12:D13) -> 1857348.2 | E14: =SUM(E12:E13) -> 2121873.1 | F14: =SUM(F12:F13) -> 2084987.7 | G14: =SUM(G12:G13) -> 2991786.8 | H14: =SUM(D14:G14) -> 9055995.9 | I14: =IFERROR((F14+G14)/(B14+C14)-1,"n/a") -> 0.063354033
A15: Gross Margin | B15: =B9-B14 -> 1161735.7 | C15: =C9-C14 -> 1663006.4 | D15: =D9-D14 -> 1098057 | E15: =E9-E14 -> 1253581.6 | F15: =F9-F14 -> 1229778.1 | G15: =G9-G14 -> 1764631 | H15: =SUM(D15:G15) -> 5346047.8 | I15: =IFERROR((F15+G15)/(B15+C15)-1,"n/a") -> 0.060064634
A17: SG&A
A18: Store Payroll | B18: =SUMIFS('GL Detail'!$E:$E,'GL Detail'!$C:$C,$A18,'GL Detail'!$A:$A,B$4) -> 499952.81 | C18: =SUMIFS('GL Detail'!$E:$E,'GL Detail'!$C:$C,$A18,'GL Detail'!$A:$A,C$4) -> 713549.69 | D18: =SUMIFS('GL Detail'!$E:$E,'GL Detail'!$C:$C,$A18,'GL Detail'!$A:$A,D$4) -> 480072.26 | E18: =SUMIFS('GL Detail'!$E:$E,'GL Detail'!$C:$C,$A18,'GL Detail'!$A:$A,E$4) -> 518083.94 | F18: =E18+E18*Drivers!$B$8 -> 528445.62 | G18: =F18+F18*Drivers!$B$8 -> 539014.53 | H18: =SUM(D18:G18) -> 2065616.3 | I18: =IFERROR((F18+G18)/(B18+C18)-1,"n/a") -> -0.12034779
A19: Marketing | B19: =SUMIFS('GL Detail'!$E:$E,'GL Detail'!$C:$C,$A19,'GL Detail'!$A:$A,B$4) -> 266791.15 | C19: =SUMIFS('GL Detail'!$E:$E,'GL Detail'!$C:$C,$A19,'GL Detail'!$A:$A,C$4) -> 375739.25 | D19: =SUMIFS('GL Detail'!$E:$E,'GL Detail'!$C:$C,$A19,'GL Detail'!$A:$A,D$4) -> 256728.45 | E19: =SUMIFS('GL Detail'!$E:$E,'GL Detail'!$C:$C,$A19,'GL Detail'!$A:$A,E$4) -> 276520.61 | F19: 165000 | G19: 240000 | H19: =SUM(D19:G19) -> 938249.06 | I19: =IFERROR((F19+G19)/(B19+C19)-1,"n/a") -> -0.36967963
A20: Occupancy | B20: =SUMIFS('GL Detail'!$E:$E,'GL Detail'!$C:$C,$A20,'GL Detail'!$A:$A,B$4) -> 210000 | C20: =SUMIFS('GL Detail'!$E:$E,'GL Detail'!$C:$C,$A20,'GL Detail'!$A:$A,C$4) -> 210000 | D20: =SUMIFS('GL Detail'!$E:$E,'GL Detail'!$C:$C,$A20,'GL Detail'!$A:$A,D$4) -> 210000 | E20: =SUMIFS('GL Detail'!$E:$E,'GL Detail'!$C:$C,$A20,'GL Detail'!$A:$A,E$4) -> 210000 | F20: =E20 -> 210000 | G20: =F20 -> 210000 | H20: =SUM(D20:G20) -> 840000 | I20: =IFERROR((F20+G20)/(B20+C20)-1,"n/a") -> 0
A21: Corporate Overhead Allocation | B21: =0 -> 0 | C21: =0 -> 0 | D21: =0 -> 0 | E21: =0 -> 0 | F21: ='[FY26 Corporate Allocations.xlsx]Alloc'!$C$4 -> 61000 | G21: ='[FY26 Corporate Allocations.xlsx]Alloc'!$D$4 -> 64000 | H21: =SUM(D21:G21) -> 125000 | I21: =IFERROR((F21+G21)/(B21+C21)-1,"n/a") -> n/a
A22: Total SG&A | B22: =SUM(B18:B21) -> 976743.96 | C22: =SUM(C18:C21) -> 1299288.9 | D22: =SUM(D18:D21) -> 946800.71 | E22: =SUM(E18:E21) -> 1004604.6 | F22: =SUM(F18:F21) -> 964445.62 | G22: =SUM(G18:G21) -> 1053014.5 | H22: =SUM(D22:G22) -> 3968865.4 | I22: =IFERROR((F22+G22)/(B22+C22)-1,"n/a") -> -0.11360677
A24: Other Income/Expense
A25: Interest Income | B25: =SUMIFS('GL Detail'!$E:$E,'GL Detail'!$C:$C,$A25,'GL Detail'!$A:$A,B$4) -> -8000 | C25: =SUMIFS('GL Detail'!$E:$E,'GL Detail'!$C:$C,$A25,'GL Detail'!$A:$A,C$4) -> -8000 | D25: =SUMIFS('GL Detail'!$E:$E,'GL Detail'!$C:$C,$A25,'GL Detail'!$A:$A,D$4) -> -8000 | E25: =SUMIFS('GL Detail'!$E:$E,'GL Detail'!$C:$C,$A25,'GL Detail'!$A:$A,E$4) -> -8000 | F25: -2500 | G25: -2500 | H25: =SUM(D25:G25) -> -21000 | I25: =IFERROR((F25+G25)/(B25+C25)-1,"n/a") -> -0.6875
A26: Depreciation | B26: =SUMIFS('GL Detail'!$E:$E,'GL Detail'!$C:$C,$A26,'GL Detail'!$A:$A,B$4) -> 45000 | C26: =SUMIFS('GL Detail'!$E:$E,'GL Detail'!$C:$C,$A26,'GL Detail'!$A:$A,C$4) -> 45000 | D26: =SUMIFS('GL Detail'!$E:$E,'GL Detail'!$C:$C,$A26,'GL Detail'!$A:$A,D$4) -> 45000 | E26: =SUMIFS('GL Detail'!$E:$E,'GL Detail'!$C:$C,$A26,'GL Detail'!$A:$A,E$4) -> 45000 | F26: =E26 -> 45000 | G26: =F26 -> 45000 | H26: =SUM(D26:G26) -> 180000 | I26: =IFERROR((F26+G26)/(B26+C26)-1,"n/a") -> 0
A27: Total Other Income/Expense | B27: =SUM(B25:B26) -> 37000 | C27: =SUM(C25:C26) -> 37000 | D27: =SUM(D25:D26) -> 37000 | E27: =SUM(E25:E26) -> 37000 | F27: =SUM(F25:F26) -> 42500 | G27: =SUM(G25:G26) -> 42500 | H27: =SUM(D27:G27) -> 159000 | I27: =IFERROR((F27+G27)/(B27+C27)-1,"n/a") -> 0.14864865
A29: Operating Profit | B29: =B15-B22 -> 184991.7 | C29: =C15-C22 -> 363717.44 | D29: =D15-D22 -> 151256.28 | E29: =E15-E22 -> 248977.09 | F29: =F15-F22 -> 265332.49 | G29: =G15-G22 -> 711616.5 | H29: =SUM(D29:G29) -> 1377182.4 | I29: =IFERROR((F29+G29)/(B29+C29)-1,"n/a") -> 0.78044963
A30: Pre-tax Income | B30: =B29-B27 -> 147991.7 | C30: =C29-C27 -> 326717.44 | D30: =D29-D27 -> 114256.28 | E30: =E29-E27 -> 211977.09 | F30: =F29-F27 -> 222832.49 | G30: =G29-G27 -> 669116.5 | H30: =SUM(D30:G30) -> 1218182.4 | I30: =IFERROR((F30+G30)/(B30+C30)-1,"n/a") -> 0.87893788

Sheet GL Detail
A1: Period | B1: Store | C1: Account | D1: Account Group | E1: Amount
A2: Q3 FY25 | B2: Store 101 | C2: In-Store Sales | D2: Net Sales | E2: 744068.25
A3: Q3 FY25 | B3: Store 102 | C3: In-Store Sales | D3: Net Sales | E3: 762689.14
A4: Q3 FY25 | B4: Store 205 | C4: In-Store Sales | D4: Net Sales | E4: 752093.27
A5: Q3 FY25 | B5: Online | C5: E-Commerce Sales | D5: Net Sales | E5: 862108.13
A6: Q3 FY25 | B6: Store 101 | C6: Merchandise Cost | D6: COGS | E6: 458752.57
A7: Q3 FY25 | B7: Store 102 | C7: Merchandise Cost | D7: COGS | E7: 464978.01
A8: Q3 FY25 | B8: Store 205 | C8: Merchandise Cost | D8: COGS | E8: 458033.8
A9: Q3 FY25 | B9: Online | C9: Merchandise Cost | D9: COGS | E9: 533775
A10: Q3 FY25 | B10: Store 101 | C10: Shrink | D10: COGS | E10: 10366.82
A11: Q3 FY25 | B11: Store 102 | C11: Shrink | D11: COGS | E11: 10620.91
A12: Q3 FY25 | B12: Store 205 | C12: Shrink | D12: COGS | E12: 10633.68
A13: Q3 FY25 | B13: Online | C13: Shrink | D13: COGS | E13: 12062.34
... A125: Q2 FY26 | B125: Online | C125: Depreciation | D125: Other Income/Expense | E125: 11250

Sheet Drivers
A1: Budget drivers
A3: Driver | B3: Value | C3: Notes
A4: In-store YoY growth (vs same qtr FY25) | B4: 0.04
A5: E-commerce YoY growth | B5: 0.12
A6: Merchandise cost % of sales | B6: 0.615
A7: Shrink % of sales | B7: 0.014
A8: Payroll QoQ growth | B8: 0.02
