Workbook
Name Coll_Base: Inputs!$B$13
Name Coll_Downside: Inputs!$B$14
Name Coll_Upside: Inputs!$B$15
Name Scenario: Inputs!$B$3
Name OpeningCash: Inputs!$B$4
Name MinCash: Inputs!$B$5

Sheet 13WCF
A1: 13-Week Cash Flow Forecast
A2: ="Scenario: "&Scenario -> Scenario: Base
A4: Week | B4: 1 | C4: 2 | D4: 3 | E4: 4 | F4: 5 | G4: 6 | H4: 7 | I4: 8 | J4: 9 | K4: 10 | L4: 11 | M4: 12 | N4: 13 | O4: 13-Wk Total
A5: Week Ending | B5: =Inputs!$B$6 -> 46318 | C5: =B5+7 -> 46325 | D5: =C5+7 -> 46332 | E5: =D5+7 -> 46339 | F5: =E5+7 -> 46346 | G5: =F5+7 -> 46353 | H5: =G5+7 -> 46360 | I5: =H5+7 -> 46367 | J5: =I5+7 -> 46374 | ... N5: =M5+7 -> 46402
A7: Beginning Cash | B7: =OpeningCash -> 1250000 | C7: =B23 -> 1362150 | D7: =C23 -> 1464550 | E7: =D23 -> 1512658.5 | F7: =E23 -> 1395134.1 | G7: =F23 -> 1321435.4 | H7: =G23 -> 1213321.3 | I7: =H23 -> 1191050.5 | J7: =I23 -> 899582 | ... N7: =M23 -> 1278662.8
A9: Receipts
A10: AR Collections | B10: =SUMIFS(tblAR[Amount],tblAR[Expected Week],B$4)*INDIRECT("Coll_"&Scenario) -> 92150 | C10: =SUMIFS(tblAR[Amount],tblAR[Expected Week],C$4)*INDIRECT("Coll_"&Scenario) -> 198550 | D10: =SUMIFS(tblAR[Amount],tblAR[Expected Week],D$4)*INDIRECT("Coll_"&Scenario) -> 87400 | E10: =SUMIFS(tblAR[Amount],tblAR[Expected Week],E$4)*INDIRECT("Coll_"&Scenario) -> 96900 | F10: =SUMIFS(tblAR[Amount],tblAR[Expected Week],F$4)*INDIRECT("Coll_"&Scenario) -> 116850 | G10: =SUMIFS(tblAR[Amount],tblAR[Expected Week],G$4)*INDIRECT("Coll_"&Scenario) -> 46550 | H10: =SUMIFS(tblAR[Amount],tblAR[Expected Week],H$4)*INDIRECT("Coll_"&Scenario) -> 47500 | I10: =SUMIFS(tblAR[Amount],tblAR[Expected Week],I$4)*INDIRECT("Coll_"&Scenario) -> 49400 | ... N10: =SUMIFS(tblAR[Amount],tblAR[Expected Week],N$4)*INDIRECT("Coll_"&Scenario) -> 368600 | O10: =SUM(B10:N10) -> 2009250
A11: New-Sales Receipts | B11: =Inputs!$B$7 -> 85000 | C11: =B11*(1+Inputs!$B$8) -> 85850 | D11: =C11*(1+Inputs!$B$8) -> 86708.5 | E11: =D11*(1+Inputs!$B$8) -> 87575.585 | F11: =E11*(1+Inputs!$B$8) -> 88451.341 | G11: =F11*(1+Inputs!$B$8) -> 89335.854 | H11: =G11*(1+Inputs!$B$8) -> 90229.213 | I11: =H11*(1+Inputs!$B$8) -> 91131.505 | J11: =I11*(1+Inputs!$B$8) -> 92042.82 | ... N11: =M11*(1+Inputs!$B$8) -> 95780.128 | O11: =SUM(B11:N11) -> 1173792.9
A12: Total Receipts | B12: =B10+B11 -> 177150 | C12: =C10+C11 -> 284400 | D12: =D10+D11 -> 174108.5 | E12: =E10+E11 -> 184475.59 | F12: =F10+F11 -> 205301.34 | G12: =G10+G11 -> 135885.85 | H12: =H10+H11 -> 137729.21 | I12: =I10+I11 -> 140531.5 | ... N12: =N10+N11 -> 464380.13 | O12: =SUM(B12:N12) -> 3183042.9
A14: Disbursements
A15: Payroll | B15: =IF(MOD(B$4,2)=0,Inputs!$B$9,0) -> 0 | C15: =IF(MOD(C$4,2)=0,Inputs!$B$9,0) -> 182000 | D15: =IF(MOD(D$4,2)=0,Inputs!$B$9,0) -> 0 | E15: =IF(MOD(E$4,2)=0,Inputs!$B$9,0) -> 182000 | F15: =IF(MOD(F$4,2)=0,Inputs!$B$9,0) -> 0 | G15: =IF(MOD(G$4,2)=0,Inputs!$B$9,0) -> 182000 | H15: =IF(MOD(H$4,2)=0,Inputs!$B$9,0) -> 0 | I15: =IF(MOD(I$4,2)=0,Inputs!$B$9,0) -> 182000 | ... N15: =IF(MOD(N$4,2)=0,Inputs!$B$9,0) -> 0 | O15: =SUM(B15:N15) -> 1092000
A16: Rent | B16: 45000 | C16: 0 | D16: 0 | E16: 0 | F16: 45000 | G16: 0 | H16: 0 | I16: 0 | J16: 45000 | K16: 0 | L16: 0 | M16: 0 | N16: 45000 | O16: =SUM(B16:N16) -> 180000
A17: AP Payments | B17: =SUMIFS(tblAP[Amount],tblAP[Pay Week],B$4) -> 20000 | C17: =SUMIFS(tblAP[Amount],tblAP[Pay Week],C$4) -> 0 | D17: =SUMIFS(tblAP[Amount],tblAP[Pay Week],D$4) -> 126000 | E17: =SUMIFS(tblAP[Amount],tblAP[Pay Week],E$4) -> 120000 | F17: =SUMIFS(tblAP[Amount],tblAP[Pay Week],F$4) -> 234000 | G17: =SUMIFS(tblAP[Amount],tblAP[Pay Week],G$4) -> 62000 | H17: =SUMIFS(tblAP[Amount],tblAP[Pay Week],H$4) -> 160000 | I17: =SUMIFS(tblAP[Amount],tblAP[Pay Week],I$4) -> 130000 | ... N17: =SUMIFS(tblAP[Amount],tblAP[Pay Week],N$4) -> 79000 | O17: =SUM(B17:N17) -> 1422000
A18: Debt Service | B18: 0 | C18: 0 | D18: 0 | E18: 0 | F18: 0 | G18: 0 | H18: 0 | I18: 120000 | J18: 0 | K18: 0 | L18: 0 | M18: 0 | N18: 0 | O18: =SUM(B18:N18) -> 120000
A19: Total Disbursements | B19: =SUM(B15:B18) -> 65000 | C19: =SUM(C15:C18) -> 182000 | D19: =SUM(D15:D18) -> 126000 | E19: =SUM(E15:E18) -> 302000 | F19: =SUM(F15:F18) -> 279000 | G19: =SUM(G15:G18) -> 244000 | H19: =SUM(H15:H18) -> 160000 | I19: =SUM(I15:I18) -> 432000 | ... N19: =SUM(N15:N18) -> 124000 | O19: =SUM(B19:N19) -> 2814000
A21: Net Cash Flow | B21: =B12-B19 -> 112150 | C21: =C12-C19 -> 102400 | D21: =D12-D19 -> 48108.5 | E21: =E12-E19 -> -117524.41 | F21: =F12-F19 -> -73698.659 | G21: =G12-G19 -> -108114.15 | H21: =H12-H19 -> -22270.787 | I21: =I12-I19 -> -291468.5 | ... N21: =N12-N19 -> 340380.13 | O21: =SUM(B21:N21) -> 369042.88
A23: Ending Cash | B23: =B7+B21 -> 1362150 | C23: =C7+C21 -> 1464550 | D23: =D7+D21 -> 1512658.5 | E23: =E7+E21 -> 1395134.1 | F23: =F7+F21 -> 1321435.4 | G23: =G7+G21 -> 1213321.3 | H23: =H7+H21 -> 1191050.5 | I23: =I7+I21 -> 899582 | ... N23: =N7+N21 -> 1619042.9
A24: Cushion vs Minimum | B24: =B23-MinCash -> 862150 | C24: =C23-MinCash -> 964550 | D24: =D23-MinCash -> 1012658.5 | E24: =E23-MinCash -> 895134.08 | F24: =F23-MinCash -> 821435.43 | G24: =G23-MinCash -> 713321.28 | H24: =H23-MinCash -> 691050.49 | I24: =I23-MinCash -> 399582 | ... N24: =N23-MinCash -> 1119042.9
A25: Lowest Ending Cash to Date | B25: =MIN($B$23:B23) -> 1362150 | C25: =MIN($B$23:C23) -> 1362150 | D25: =MIN($B$23:D23) -> 1362150 | E25: =MIN($B$23:E23) -> 1362150 | F25: =MIN($B$23:F23) -> 1321435.4 | G25: =MIN($B$23:G23) -> 1213321.3 | H25: =MIN($B$23:H23) -> 1191050.5 | I25: =MIN($B$23:I23) -> 899582 | ... N25: =MIN($B$23:N23) -> 899582

Sheet Inputs
A1: Cash forecast inputs
A3: Scenario | B3: Base
A4: Opening Cash | B4: 1250000
A5: Minimum Cash | B5: 500000
A6: Week 1 Ending | B6: 46318
A7: New-sales receipts wk1 | B7: 85000
A8: New-sales weekly growth | B8: 0.01
A9: Biweekly payroll | B9: 182000
A12: Scenario | B12: Collection Rate
A13: Base | B13: 0.95
A14: Downside | B14: 0.82
A15: Upside | B15: 1

Sheet AR Aging
A1: Invoice | B1: Customer | C1: Amount | D1: Due Date | E1: Expected Week
A2: INV-5002 | B2: Customer 3 | C2: 81000 | D2: 46400 | E2: 13
A3: INV-5003 | B3: Customer 4 | C3: 70000 | D3: 46323 | E3: 2
A4: INV-5004 | B4: Customer 5 | C4: 41000 | D4: 46400 | E4: 13
A5: INV-5005 | B5: Customer 6 | C5: 8000 | D5: 46316 | E5: 1
A6: INV-5006 | B6: Customer 7 | C6: 92000 | D6: 46330 | E6: 3
A7: INV-5007 | B7: Customer 8 | C7: 68000 | D7: 46379 | E7: 10
A8: INV-5008 | B8: Customer 9 | C8: 55000 | D8: 46400 | E8: 13
A9: INV-5009 | B9: Customer 10 | C9: 10000 | D9: 46351 | E9: 6
A10: INV-5010 | B10: Customer 11 | C10: 70000 | D10: 46344 | E10: 5
A11: INV-5011 | B11: Customer 12 | C11: 33000 | D11: 46400 | E11: 13
A12: INV-5012 | B12: Customer 1 | C12: 60000 | D12: 46393 | E12: 12
A13: INV-5013 | B13: Customer 2 | C13: 77000 | D13: 46372 | E13: 9
... A41: INV-5041 | B41: Customer 6 | C41: 92000 | D41: 46379 | E41: 10

Sheet AP Schedule
A1: Vendor | B1: Amount | C1: Pay Week | D1: Category
A2: Vendor 3 | B2: 44000 | C2: 5 | D2: Capex
A3: Vendor 4 | B3: 53000 | C3: 4 | D3: Opex
A4: Vendor 5 | B4: 22000 | C4: 4 | D4: Capex
A5: Vendor 6 | B5: 6000 | C5: 4 | D5: COGS
A6: Vendor 7 | B6: 26000 | C6: 13 | D6: COGS
A7: Vendor 8 | B7: 47000 | C7: 11 | D7: Capex
A8: Vendor 9 | B8: 44000 | C8: 11 | D8: Opex
A9: Vendor 1 | B9: 54000 | C9: 7 | D9: Opex
A10: Vendor 2 | B10: 67000 | C10: 3 | D10: COGS
A11: Vendor 3 | B11: 59000 | C11: 3 | D11: Capex
A12: Vendor 4 | B12: 55000 | C12: 12 | D12: COGS
A13: Vendor 5 | B13: 36000 | C13: 8 | D13: COGS
... A31: Vendor 5 | B31: 55000 | C31: 11 | D31: Opex
